snmp_passpersist.py
snmp_passpersist-2.1.0.dist-info/LICENSE
snmp_passpersist-2.1.0.dist-info/METADATA
snmp_passpersist-2.1.0.dist-info/WHEEL
snmp_passpersist-2.1.0.dist-info/top_level.txt
snmp_passpersist-2.1.0.dist-info/RECORD
