Metadata-Version: 2.1
Name: snmp-passpersist
Version: 2.1.0
Summary: SNMP passpersist backend for Net-SNMP
Home-page: http://github.com/nagius/snmp_passpersist
Author: Nicolas Agius
Author-email: nicolas.agius@lps-it.fr
License: GPLv3
Keywords: snmp net-snmp
Platform: UNKNOWN
Classifier: Intended Audience :: Developers
Classifier: License :: OSI Approved :: GNU General Public License (GPL)
Classifier: Development Status :: 5 - Production/Stable
Classifier: Operating System :: POSIX :: Linux
Classifier: Topic :: System :: Monitoring
